ggly/__init__.py
ggly/aes.py
ggly/core.py
ggly/data_loader.py
ggly/coords/__init__.py
ggly/coords/base.py
ggly/coords/cartesian.py
ggly/coords/flip.py
ggly/facets/__init__.py
ggly/facets/base.py
ggly/facets/grid.py
ggly/facets/wrap.py
ggly/geoms/__init__.py
ggly/geoms/bar.py
ggly/geoms/base.py
ggly/geoms/boxplot.py
ggly/geoms/histogram.py
ggly/geoms/line.py
ggly/geoms/path.py
ggly/geoms/point.py
ggly/geoms/smooth.py
ggly/scales/__init__.py
ggly/scales/base.py
ggly/scales/color.py
ggly/scales/continuous.py
ggly/scales/discrete.py
ggly/stats/__init__.py
ggly/stats/base.py
ggly/stats/contour.py
ggly/stats/count.py
ggly/stats/density.py
ggly/stats/smooth.py
ggly/themes/__init__.py
ggly/themes/base.py
ggly/themes/classic.py
ggly/themes/dark.py
ggly/themes/ggplot2.py
ggly/themes/lyric.py
ggly/themes/minimal.py
ggly/themes/theme_elements.py
ggly/utils/__init__.py
ggly/utils/colors.py
ggly-0.1.0a2.dist-info/METADATA
ggly-0.1.0a2.dist-info/WHEEL
ggly-0.1.0a2.dist-info/licenses/LICENSE
ggly-0.1.0a2.dist-info/RECORD
