Metadata-Version: 2.4
Name: ggly
Version: 0.1.0a2
Summary: ggplot2-like Grammar of Graphics for Python with Plotly
License-File: LICENSE
Classifier: Development Status :: 3 - Alpha
Classifier: License :: OSI Approved :: MIT License
Classifier: Operating System :: OS Independent
Classifier: Programming Language :: Python :: 3
Requires-Python: >=3.10
Requires-Dist: numpy
Requires-Dist: pandas
Requires-Dist: plotly-resampler>=0.10.0
Requires-Dist: plotly>=5.15.0
Requires-Dist: scipy
Requires-Dist: statsmodels>=0.14.4
Provides-Extra: dev
Requires-Dist: ipykernel; extra == 'dev'
Requires-Dist: nbformat>=5.10.4; extra == 'dev'
Requires-Dist: pytest>=8.3.5; extra == 'dev'
